checkpaste/__init__.py
checkpaste/cli.py
checkpaste/client.py
checkpaste/clipboard_utils.py
checkpaste/config.py
checkpaste/discovery.py
checkpaste/run.py
checkpaste/server.py
checkpaste/utils.py
checkpaste-0.1.13.dist-info/METADATA
checkpaste-0.1.13.dist-info/WHEEL
checkpaste-0.1.13.dist-info/entry_points.txt
checkpaste-0.1.13.dist-info/licenses/LICENSE
checkpaste-0.1.13.dist-info/RECORD
