Metadata-Version: 2.4
Name: checkpaste
Version: 0.1.13
Summary: A cross-platform tool to sync text and files between devices on the same local network.
Project-URL: Homepage, https://github.com/mithunbarath/checkpaste
Author-email: Mithun Barath M R <barathmithun1548@gmail.com>
License-File: LICENSE
Classifier: License :: OSI Approved :: MIT License
Classifier: Operating System :: OS Independent
Classifier: Programming Language :: Python :: 3
Requires-Python: >=3.8
Requires-Dist: fastapi>=0.68.0
Requires-Dist: pillow>=10.0.0
Requires-Dist: pyngrok>=5.0.0
Requires-Dist: pyperclip>=1.8.0
Requires-Dist: python-multipart>=0.0.5
Requires-Dist: pywin32>=306; sys_platform == 'win32'
Requires-Dist: requests>=2.26.0
Requires-Dist: rich>=10.0.0
Requires-Dist: typer>=0.4.0
Requires-Dist: uvicorn>=0.15.0
Requires-Dist: zeroconf>=0.36.0
